airflow/providers/qlik_sense_cloud/__init__.py
airflow/providers/qlik_sense_cloud/hooks/__init__.py
airflow/providers/qlik_sense_cloud/hooks/qlik_sense_hook.py
airflow/providers/qlik_sense_cloud/operators/__init__.py
airflow/providers/qlik_sense_cloud/operators/qlik_sense_cloud_automation.py
airflow/providers/qlik_sense_cloud/operators/qlik_sense_cloud_reload.py
airflow/providers/qlik_sense_cloud/operators/qlik_sense_cloud_report.py
airflow_provider_qlik_sense_cloud_rac-0.0.1.dist-info/LICENSE
airflow_provider_qlik_sense_cloud_rac-0.0.1.dist-info/METADATA
airflow_provider_qlik_sense_cloud_rac-0.0.1.dist-info/WHEEL
airflow_provider_qlik_sense_cloud_rac-0.0.1.dist-info/entry_points.txt
airflow_provider_qlik_sense_cloud_rac-0.0.1.dist-info/top_level.txt
airflow_provider_qlik_sense_cloud_rac-0.0.1.dist-info/RECORD
