Metadata-Version: 2.1
Name: airflow-provider-qlik-sense-cloud-rac
Version: 0.0.1
Summary: Airflow package provider to reload apps/task/automation from Qlik Sense Cloud.
Home-page: 
Author: Clement Parsy
Author-email: cparsy@decideom.fr
License: Apache License 2.0
Classifier: Framework :: Apache Airflow
Classifier: Framework :: Apache Airflow :: Provider
Requires-Python: ~=3.9
License-File: LICENSE
Requires-Dist: apache-airflow >=2.10
Requires-Dist: qlik-sdk
